Metadata-Version: 2.1
Name: pyprankerror
Version: 1.0.1
Summary: An example of a package developed with pyenv, built with build using setuptools, uploaded to PyPI using twine, and distributed via pip.
Author-email: Foo Barstein <foo.barstein@onepotcooking.com>
License:                     GNU GENERAL PUBLIC LICENSE
Project-URL: Homepage, https://github.com/software-students-fall2023/3-python-package-exercise-plant-3-0
Project-URL: Repository, https://github.com/software-students-fall2023/3-python-package-exercise-plant-3-0.git
Project-URL: Bug Tracker, https://github.com/software-students-fall2023/3-python-package-exercise-plant-3-0/issues
Keywords: python,package,build,tutorial
Classifier: Programming Language :: Python :: 3
Classifier: Intended Audience :: Education
Classifier: License :: OSI Approved :: GNU General Public License v3 (GPLv3)
Classifier: Operating System :: OS Independent
Requires-Python: >=3.7
License-File: LICENSE
Provides-Extra: dev
Requires-Dist: pytest; extra == "dev"
